{
  "info": {
    "name": "ReliaQuest-Task",
    "schema": "https://schema.getpostman.com/json/collection/v2.1.0/collection.json"
  },
  "item": [
    {
      "name": "List of employees",
      "request": {
        "method": "GET",
        "header": [
          {
            "key": "x-api-key",
            "value": "{{apiKey}}",
            "type": "text"
          }
        ],
        "url": {
          "raw": "http://localhost:8080/api/v1/employee",
          "protocol": "http",
          "host": [
            "localhost"
          ],
          "port": "8080",
          "path": [
            "api",
            "v1",
            "employee"
          ]
        }
      },
      "response": []
    },
    {
      "name": "Employee by UUID",
      "request": {
        "method": "GET",
        "header": [
          {
            "key": "x-api-key",
            "value": "{{apiKey}}",
            "type": "text"
          }
        ],
        "url": {
          "raw": "http://localhost:8080/api/v1/employee/2e3c8806-9f76-43db-b484-3b4ec64ea2b3",
          "protocol": "http",
          "host": [
            "localhost"
          ],
          "port": "8080",
          "path": [
            "api",
            "v1",
            "employee",
            "2e3c8806-9f76-43db-b484-3b4ec64ea2b3"
          ]
        }
      },
      "response": []
    },
    {
      "name": "Create Employee",
      "request": {
        "method": "POST",
        "header": [
          {
            "key": "x-api-key",
            "value": "{{apiKey}}",
            "type": "text"
          }
        ],
        "body": {
          "mode": "raw",
          "raw": "{\r\n    \"firstName\": \"Tony\",\r\n    \"lastName\": \"Stark\",\r\n    \"salary\": 1600000,\r\n    \"age\": 35,\r\n    \"jobTitle\": \"Software Developer\",\r\n    \"email\": \"tonystark@avengers.com\",\r\n    \"contractHireDate\": \"2025-01-01T09:00:00+05:30\",\r\n    \"contractTerminationDate\": \"2026-01-02T03:30:00Z\"\r\n}",
          "options": {
            "raw": {
              "language": "json"
            }
          }
        },
        "url": {
          "raw": "http://localhost:8080/api/v1/employee",
          "protocol": "http",
          "host": [
            "localhost"
          ],
          "port": "8080",
          "path": [
            "api",
            "v1",
            "employee"
          ]
        }
      },
      "response": []
    }
  ],
  "event": [
    {
      "listen": "prerequest",
      "script": {
        "type": "text/javascript",
        "packages": {},
        "requests": {},
        "exec": [
          ""
        ]
      }
    },
    {
      "listen": "test",
      "script": {
        "type": "text/javascript",
        "packages": {},
        "requests": {},
        "exec": [
          ""
        ]
      }
    }
  ],
  "variable": [
    {
      "key": "apiKey",
      "value": "some-super-secret-key"
    }
  ]
}